{
    "mouseover": [
        {
            "selector": ".title a",
            "text": ["要看看 {text} 么？"]
        },
        {
            "selector": ".searchbox",
            "text": ["在找什么东西呢，需要帮忙吗？"]
        }
    ],
    "click": [
        {
            "selector": "#landlord #live2d",
            "text": [
                "献给所有尚未知晓爱的人~~",
                "一瞬间的，邂逅、再会、拥抱。",
                "为了你，我无所不能！",
                "我想与你一起，细数万千繁星",
                "再摸的话我也是会生气的哟！⌇●﹏●⌇",
                "总有一天我会踩著湖上的落叶渡河给你看喔！",
                "从我拥抱你的那一刻开始，我们的命运便就此交织在一起。",
                "语言的含义有内外两层，说出口的并不是全部"
            ]
        }
    ]
}